MANIFEST.in
README.rst
setup.py
bottle_cork.egg-info/PKG-INFO
bottle_cork.egg-info/SOURCES.txt
bottle_cork.egg-info/dependency_links.txt
bottle_cork.egg-info/requires.txt
bottle_cork.egg-info/top_level.txt
cork/__init__.py
cork/backends.py
cork/base_backend.py
cork/cork.py
cork/json_backend.py
cork/mongodb_backend.py
cork/sessions.py
cork/sqlalchemy_backend.py
cork/sqlite_backend.py
examples/bugtest.py
examples/cork.py
examples/example.db
examples/example2.db
examples/recreate_example_conf.py
examples/simple_webapp.py
examples/simple_webapp_decorated.py
examples/simple_webapp_flask.py
examples/simple_webapp_using_mongodb.py
examples/simple_webapp_using_sqlite.py
examples/simple_webapp_using_sqlite_mytest.py
examples/static_file
examples/test_real_ssl_smtp.py
examples/example_conf/register.json
examples/example_conf/roles.json
examples/example_conf/users.json
examples/templates/admin_page.html
examples/templates/login_form.html
examples/templates/password_change_form.html
examples/templates/password_reset_email.html
examples/templates/registration_email.html
examples/views/admin_page.tpl
examples/views/login_form.tpl
examples/views/password_change_form.tpl
examples/views/password_reset_email.tpl
examples/views/registration_email.tpl
tests/multiparam.py
tests/simple_webapp.py
tests/simple_webapp_decorated.py
tests/simple_webapp_flask.py
tests/test.py
tests/test_flask.py
tests/test_functional_json.py
tests/test_functional_mongodb_instance.py
tests/test_functional_mysql_instance.py
tests/test_functional_sqlalchemy_sqlite_in_memory.py
tests/test_scrypt.py
tests/test_sqlite.py
tests/test_webtest_bottle.py
tests/test_webtest_decorated.py
tests/test_webtest_flask.py
tests/test_webtest_parallel.py
tests/testutils.py