Metadata-Version: 1.1
Name: bottle-cork
Version: 0.11.1
Summary: Authentication/Authorization library for Bottle
Home-page: http://cork.firelet.net/
Author: Federico Ceratto
Author-email: federico.ceratto@gmail.com
License: LGPLv3+
Platform: Linux
Classifier: Environment :: Console
Classifier: License :: OSI Approved :: GNU Lesser General Public License v3 (LGPLv3)
Classifier: Natural Language :: English
Classifier: Operating System :: POSIX :: Linux
Classifier: Programming Language :: Python
Classifier: Topic :: Internet :: WWW/HTTP :: WSGI
Classifier: Topic :: Security
Classifier: Topic :: Software Development :: Libraries :: Python Modules
